setup.py
jupiter_http/AuthFactory.py
jupiter_http/HttpDecorator.py
jupiter_http/Jinja2Filter.py
jupiter_http/Jinja2Setting.py
jupiter_http/LoggerFactory.py
jupiter_http/RequestHandler.py
jupiter_http/ResponseFactory.py
jupiter_http/Route.py
jupiter_http/__init__.py
jupiter_http.egg-info/PKG-INFO
jupiter_http.egg-info/SOURCES.txt
jupiter_http.egg-info/dependency_links.txt
jupiter_http.egg-info/requires.txt
jupiter_http.egg-info/top_level.txt